[{"type":2,"colour":0,"left":0,"right":365,"top":0,"bottom":235,"content":4294967295,"tooltip":65535},{"type":25,"colour":0,"left":1,"right":364,"top":1,"bottom":16,"content":1466,"tooltip":65535},{"type":9,"colour":0,"left":351,"right":363,"top":2,"bottom":14,"content":2321,"tooltip":60},{"type":1,"colour":1,"left":0,"right":365,"top":44,"bottom":234,"content":4294967295,"tooltip":65535},{"type":8,"colour":1,"left":3,"right":33,"top":18,"bottom":44,"content":536873299,"tooltip":65535},{"type":8,"colour":1,"left":34,"right":64,"top":18,"bottom":44,"content":536873299,"tooltip":65535},{"type":5,"colour":1,"left":3,"right":362,"top":45,"bottom":122,"content":4294967295,"tooltip":65535},{"type":9,"colour":1,"left":10,"right":355,"top":130,"bottom":161,"content":2312,"tooltip":65535},{"type":9,"colour":1,"left":10,"right":355,"top":130,"bottom":161,"content":2314,"tooltip":65535},{"type":9,"colour":1,"left":10,"right":355,"top":170,"bottom":201,"content":2313,"tooltip":65535},{"type":11,"colour":1,"left":262,"right":361,"top":218,"bottom":232,"content":186,"tooltip":65535},{"type":11,"colour":1,"left":262,"right":361,"top":218,"bottom":232,"content":187,"tooltip":65535}]